puddlestuff/__init__.py
puddlestuff/about.py
puddlestuff/action_shortcuts.py
puddlestuff/actiondlg.py
puddlestuff/audio_filter.py
puddlestuff/confirmations.py
puddlestuff/constants.py
puddlestuff/findfunc.py
puddlestuff/funcprint.py
puddlestuff/functions.py
puddlestuff/functions_dialogs.py
puddlestuff/genres.py
puddlestuff/helperwin.py
puddlestuff/loadshortcuts.py
puddlestuff/logger.py
puddlestuff/m3u.py
puddlestuff/musiclib.py
puddlestuff/pluginloader.py
puddlestuff/puddleobjects.py
puddlestuff/puddlesettings.py
puddlestuff/puddletag.py
puddlestuff/resource.py
puddlestuff/shortcutsettings.py
puddlestuff/tagmodel.py
puddlestuff/translations.py
puddlestuff/util.py
puddlestuff/audioinfo/__init__.py
puddlestuff/audioinfo/_compatid3.py
puddlestuff/audioinfo/apev2.py
puddlestuff/audioinfo/constants.py
puddlestuff/audioinfo/id3.py
puddlestuff/audioinfo/mp4.py
puddlestuff/audioinfo/tag_versions.py
puddlestuff/audioinfo/util.py
puddlestuff/audioinfo/vorbis.py
puddlestuff/audioinfo/wma.py
puddlestuff/data/appicon.svg
puddlestuff/data/application-exit.png
puddlestuff/data/caseconversion.action
puddlestuff/data/configure.png
puddlestuff/data/document-edit.png
puddlestuff/data/document-save.png
puddlestuff/data/edit-copy.png
puddlestuff/data/edit-cut.png
puddlestuff/data/edit-delete.png
puddlestuff/data/edit-find-replace.png
puddlestuff/data/edit-paste.png
puddlestuff/data/edit-select-all.png
puddlestuff/data/edit-undo.png
puddlestuff/data/folder-new.png
puddlestuff/data/folder.png
puddlestuff/data/help-about.png
puddlestuff/data/list-add.png
puddlestuff/data/list-remove.png
puddlestuff/data/media-playback-start.png
puddlestuff/data/menus
puddlestuff/data/puddlelogo.png
puddlestuff/data/puddlelogo.svg
puddlestuff/data/puddletag.autonumber.png
puddlestuff/data/puddletag.filetotag.png
puddlestuff/data/puddletag.renamedirs.png
puddlestuff/data/puddletag.tagtofile.png
puddlestuff/data/puddletag.textfiletotag.png
puddlestuff/data/quickopen-function.png
puddletag-2.5.0.dist-info/licenses/LICENSE
puddletag-2.5.0.dist-info/METADATA
puddletag-2.5.0.dist-info/WHEEL
puddletag-2.5.0.dist-info/top_level.txt
puddletag-2.5.0.dist-info/RECORD
