Metadata-Version: 2.4
Name: puddletag
Version: 2.5.0
Summary: Powerful, simple, audio tag editor
Home-page: https://docs.puddletag.net/
Download-URL: https://github.com/puddletag/puddletag
Author: puddletag developers
License: GNU General Public License v3 or later (GPLv3+)
Keywords: tagging ogg mp3 apev2 mp4 id3
Classifier: Development Status :: 5 - Production/Stable
Classifier: Intended Audience :: End Users/Desktop
Classifier: Natural Language :: English
Classifier: Operating System :: POSIX :: Linux
Classifier: Programming Language :: Python :: 3 :: Only
Classifier: Topic :: Multimedia :: Sound/Audio :: Editors
Requires-Python: >=3.7
License-File: LICENSE
Requires-Dist: audioread==3.0.1
Requires-Dist: certifi==2024.7.4
Requires-Dist: charset-normalizer==2.0.10
Requires-Dist: configobj==5.0.9
Requires-Dist: idna==3.7
Requires-Dist: levenshtein==0.27.1
Requires-Dist: lxml==6.0.0
Requires-Dist: mutagen==1.47.0
Requires-Dist: pyacoustid==1.3.0
Requires-Dist: pyparsing==3.2.3
Requires-Dist: pyqt5==5.15.11
Requires-Dist: pyqt5-qt5==5.15.2
Requires-Dist: pyqt5-sip==12.15.0
Requires-Dist: rapidfuzz==3.10.0
Requires-Dist: requests==2.32.4
Requires-Dist: unidecode==1.4.0
Requires-Dist: urllib3==2.5.0
Dynamic: author
Dynamic: classifier
Dynamic: description
Dynamic: description-content-type
Dynamic: download-url
Dynamic: home-page
Dynamic: keywords
Dynamic: license
Dynamic: license-file
Dynamic: requires-dist
Dynamic: requires-python
Dynamic: summary
